{
	"info": {
		"_postman_id": "e6643033-9201-41fa-8a22-49633022d5e9",
		"name": "The Node.js Master Class - Homework Assignment #1",
		"schema": "https://schema.getpostman.com/json/collection/v2.1.0/collection.json"
	},
	"item": [
		{
			"name": "Hello",
			"request": {
				"method": "POST",
				"header": [],
				"body": {},
				"url": {
					"raw": "http://localhost:3000/hello",
					"protocol": "http",
					"host": [
						"localhost"
					],
					"port": "3000",
					"path": [
						"hello"
					]
				}
			},
			"response": []
		}
	]
}